addCode.py
addCode-0.0.2.dist-info/METADATA
addCode-0.0.2.dist-info/WHEEL
addCode-0.0.2.dist-info/top_level.txt
addCode-0.0.2.dist-info/RECORD
